{
  "closed_trades": 1746,
  "win_rate": 45.7,
  "cumulative_pnl": 641.1,
  "avg_return": 0.37,
  "profit_factor": 1.17,
  "best_trade": 109.0,
  "trades_this_week": 95,
  "max_drawdown": -56.9,
  "open_positions": 47,
  "version": "18.18",
  "inception_date": "Jan 01, 2025",
  "last_updated": "Mar 15, 2026 \u00b7 11:14 AM",
  "equity_curve": [
    {
      "date": "2026-01-05",
      "value": -1.42
    },
    {
      "date": "2026-01-06",
      "value": 2.86
    },
    {
      "date": "2026-01-07",
      "value": 3.8
    },
    {
      "date": "2026-01-08",
      "value": 13.21
    },
    {
      "date": "2026-01-09",
      "value": 2.1
    },
    {
      "date": "2026-01-12",
      "value": -6.43
    },
    {
      "date": "2026-01-13",
      "value": -4.45
    },
    {
      "date": "2026-01-14",
      "value": -0.67
    },
    {
      "date": "2026-01-15",
      "value": 0.94
    },
    {
      "date": "2026-01-16",
      "value": 1.87
    },
    {
      "date": "2026-01-19",
      "value": -6.88
    },
    {
      "date": "2026-01-20",
      "value": 3.52
    },
    {
      "date": "2026-01-21",
      "value": 15.99
    },
    {
      "date": "2026-01-22",
      "value": 6.77
    },
    {
      "date": "2026-01-23",
      "value": 21.12
    },
    {
      "date": "2026-01-27",
      "value": 38.89
    },
    {
      "date": "2026-01-28",
      "value": 31.5
    },
    {
      "date": "2026-01-29",
      "value": 43.8
    },
    {
      "date": "2026-01-30",
      "value": 54.71
    },
    {
      "date": "2026-02-02",
      "value": 55.66
    },
    {
      "date": "2026-02-03",
      "value": 37.19
    },
    {
      "date": "2026-02-04",
      "value": 32.32
    },
    {
      "date": "2026-02-05",
      "value": 51.04
    },
    {
      "date": "2026-02-06",
      "value": 55.88
    },
    {
      "date": "2026-02-09",
      "value": 76.65
    },
    {
      "date": "2026-02-10",
      "value": 91.46
    },
    {
      "date": "2026-02-11",
      "value": 81.76
    },
    {
      "date": "2026-02-12",
      "value": 86.66
    },
    {
      "date": "2026-02-13",
      "value": 92.53
    },
    {
      "date": "2026-02-16",
      "value": 87.8
    },
    {
      "date": "2026-02-19",
      "value": 88.37
    },
    {
      "date": "2026-02-20",
      "value": 91.71
    },
    {
      "date": "2026-02-26",
      "value": 91.31
    },
    {
      "date": "2026-03-05",
      "value": 129.36
    },
    {
      "date": "2026-03-06",
      "value": 133.58
    },
    {
      "date": "2026-03-09",
      "value": 130.58
    },
    {
      "date": "2026-03-10",
      "value": 116.31
    },
    {
      "date": "2026-03-11",
      "value": 115.35
    },
    {
      "date": "2026-03-12",
      "value": 128.21
    }
  ]
}